LICENSE
README.md
setup.cfg
setup.py
pelican/plugins/sphinxsearch/__init__.py
pelican/plugins/sphinxsearch/sphinxsearch.py
pelican_sphinxsearch.egg-info/PKG-INFO
pelican_sphinxsearch.egg-info/SOURCES.txt
pelican_sphinxsearch.egg-info/dependency_links.txt
pelican_sphinxsearch.egg-info/not-zip-safe
pelican_sphinxsearch.egg-info/requires.txt
pelican_sphinxsearch.egg-info/top_level.txt