Metadata-Version: 2.1
Name: pelican-sphinxsearch
Version: 1.1
Summary: A Pelican plugin to provide a support of Sphinxsearch tool, allowing users to search keywords on the texts proposed on a website generated with Pelican (a static site generator written in Python).
Home-page: https://github.com/ysard/sphinxsearch-for-pelican
Author: Ysard
Author-email: ysard@users.noreply.github.com
License: UNKNOWN
Keywords: pelican,sphinxsearch,search index
Platform: UNKNOWN
Classifier: Development Status :: 5 - Production/Stable
Classifier: Intended Audience :: Developers
Classifier: Intended Audience :: System Administrators
Classifier: Intended Audience :: End Users/Desktop
Classifier: Programming Language :: Python :: 3
Classifier: Programming Language :: Python :: 3.6
Classifier: Programming Language :: Python :: 3.7
Classifier: Programming Language :: Python :: 3.8
Classifier: Programming Language :: Python :: 3.9
Classifier: Programming Language :: Python :: 3.10
Classifier: License :: OSI Approved :: GNU Affero General Public License v3 or later (AGPLv3+)
Provides-Extra: dev
